pyresu/__init__.py
pyresu/core.py
pyresu/models.py
pyresu/preprocessing.py
pyresu/simulation.py
pyresu-0.1.0.dist-info/licenses/LICENSE
pyresu-0.1.0.dist-info/METADATA
pyresu-0.1.0.dist-info/WHEEL
pyresu-0.1.0.dist-info/top_level.txt
pyresu-0.1.0.dist-info/RECORD
