Metadata-Version: 2.4
Name: pyresu
Version: 0.1.0
Summary: Rectified Spectral Units (ReSU) implementation based on Qin et al. (2025)
Author-email: kuslavicek <kuslavicek@gmail.com>
Project-URL: Homepage, https://github.com/kuslavicek/pyresu
Project-URL: Bug Tracker, https://github.com/kuslavicek/pyresu/issues
Classifier: Programming Language :: Python :: 3
Classifier: License :: OSI Approved :: MIT License
Classifier: Operating System :: OS Independent
Requires-Python: >=3.8
License-File: LICENSE
Requires-Dist: numpy>=1.20.0
Requires-Dist: scipy>=1.7.0
Provides-Extra: dev
Requires-Dist: pytest>=7.0.0; extra == "dev"
Requires-Dist: hypothesis>=6.0.0; extra == "dev"
Dynamic: license-file
